yasim_sc/__init__.py
yasim_sc/__main__.py
yasim_sc/_main/__init__.py
yasim_sc/_main/_generate_barcode.py
yasim_sc/_main/_generate_barcoded_isoform_replicates.py
yasim_sc/_main/_sample_pcg.py
yasim_sc/_main/art.py
yasim_sc/helper/__init__.py
yasim_sc/helper/rna_seq.py
yasim_sctcr/__init__.py
yasim_sctcr/__main__.py
yasim_sctcr/_main/__init__.py
yasim_sctcr/_main/_exclude_tcr_from_gtf.py
yasim_sctcr/_main/convert_anndata.py
yasim_sctcr/_main/generate_tcr_cache.py
yasim_sctcr/_main/generate_tcr_clonal_expansion.py
yasim_sctcr/_main/generate_tcr_depth.py
yasim_sctcr/_main/rearrange_tcr.py
yasim_sctcr/_main/scaffold.py
yasim_sctcr/_main/sample_data/.gitignore
yasim_sctcr/_main/sample_data/cdr3_deletion_table.min.json
yasim_sctcr/_main/sample_data/cdr3_insertion_table.min.json
yasim_sctcr/helper/__init__.py
yasim_sctcr/helper/tcr.py
yasim_sctcr-1.0.0.dist-info/Copying.md
yasim_sctcr-1.0.0.dist-info/METADATA
yasim_sctcr-1.0.0.dist-info/WHEEL
yasim_sctcr-1.0.0.dist-info/top_level.txt
yasim_sctcr-1.0.0.dist-info/RECORD
