Metadata-Version: 2.1
Name: yasim_sctcr
Version: 1.0.0
Summary: yasim_sctcr -- Yet Another SIMulator for Single-Cell T-Cell Receptor Sequencing (scTCR-Seq)
Author-email: YU Zhejian <Zhejian.23@intl.zju.edu.cn>, TIAN Ruonan <Ruonan.21@intl.zju.edu.cn>, WU Jiaxin <Jiaxin2.22@intl.zju.edu.cn>, "LIU Wanlu (Correspondence)" <wanluliu@intl.zju.edu.cn>
Project-URL: Source, https://github.com/WanluLiuLab/yasim-sctcr
Project-URL: Documentation, https://labw.org/yasim-sctcr-docs/
Classifier: Development Status :: 4 - Beta
Classifier: Environment :: Console
Classifier: Intended Audience :: Developers
Classifier: Intended Audience :: Healthcare Industry
Classifier: Intended Audience :: Science/Research
Classifier: License :: OSI Approved :: MIT License
Classifier: Natural Language :: English
Classifier: Operating System :: MacOS :: MacOS X
Classifier: Operating System :: POSIX
Classifier: Programming Language :: Python :: 3 :: Only
Classifier: Programming Language :: Python :: 3.8
Classifier: Programming Language :: Python :: 3.9
Classifier: Programming Language :: Python :: 3.10
Classifier: Programming Language :: Python :: 3.11
Classifier: Programming Language :: Python :: 3.12
Classifier: Programming Language :: Python :: Implementation :: CPython
Classifier: Topic :: Scientific/Engineering :: Bio-Informatics
Classifier: Topic :: Utilities
Requires-Python: >=3.8
License-File: Copying.md
Requires-Dist: yasim ==3.2.1
